{
  "$schema": "https://turbo.build/schema.json",
  "pipeline": {
    "build": {
      "dependsOn": ["^build"],
      "outputs": ["dist/**", "es/**", "umd/**"],
      "env": ["API_KEY"]
    },
    "@shopware-ag/meteor-component-library#build:storybook": {
      "outputs": ["storybook-static/**"],
      "env": ["SHOW_INTERACTIONS"]
    },
    "lint:all": {
      "outputs": []
    },
    "lint:types": {
      "outputs": []
    },
    "lint:eslint": {
      "outputs": []
    },
    "format:check": {},
    "test:unit": {
      "outputs": []
    },
    "test:e2e": {
      "outputs": []
    },
    "@shopware-ag/meteor-component-library#test:storybook": {
      "outputs": []
    }
  }
}
